fisheye/__init__.py
fisheye/app.py
fisheye/camera.py
fisheye/cli.py
fisheye/projection.py
fisheye/schemas.py
fisheye_tools-0.1.1.dist-info/LICENSE
fisheye_tools-0.1.1.dist-info/METADATA
fisheye_tools-0.1.1.dist-info/WHEEL
fisheye_tools-0.1.1.dist-info/entry_points.txt
fisheye_tools-0.1.1.dist-info/RECORD
