Metadata-Version: 2.1
Name: fisheye-tools
Version: 0.1.1
Summary: 
Author: TERBOUCHE Hacene
Author-email: hacene.terbouche@gmail.com
Requires-Python: >=3.9,<3.13
Classifier: Programming Language :: Python :: 3
Classifier: Programming Language :: Python :: 3.9
Classifier: Programming Language :: Python :: 3.10
Classifier: Programming Language :: Python :: 3.11
Classifier: Programming Language :: Python :: 3.12
Requires-Dist: numpy (>=1.25,<2.0)
Requires-Dist: opencv-python (>=4.10.0.84,<5.0.0.0)
Requires-Dist: pyopengl (>=3.1.7,<4.0.0)
Requires-Dist: pyopengl-accelerate (>=3.1.7,<4.0.0)
Requires-Dist: pyqtgraph (>=0.13.7,<0.14.0)
Requires-Dist: pyside6 (>=6.7.3,<7.0.0)
Requires-Dist: tqdm (>=4.66.2,<5.0.0)
Requires-Dist: typer (>=0.12.5,<0.13.0)
